[
  {
    "httpRequest": {
      "method": "GET",
      "path": "/api/stop/findByAddress"
    },
    "httpResponse": {
      "body": [
        {
          "stop_num": "2051",
          "stop_address": "Monkstown Ave",
          "stop_location": "Stradbrook Rd",
          "stop_lat": "53.2864489905228",
          "stop_lon": "-6.15989900807043"
        },
        {
          "stop_num": "6086",
          "stop_address": "Link Road",
          "stop_location": "Deansgrange Road",
          "stop_lat": "53.286244480501",
          "stop_lon": "-6.16529247984307"
        },
        {
          "stop_num": "3161",
          "stop_address": "Deansgrange Rd",
          "stop_location": "Abbey Road",
          "stop_lat": "53.2870045612498",
          "stop_lon": "-6.16795979645646"
        },
        {
          "stop_num": "3162",
          "stop_address": "Rowan Pk",
          "stop_location": "Rowan Park Ave",
          "stop_lat": "53.2897488037638",
          "stop_lon": "-6.1675573564683"
        },
        {
          "stop_num": "3163",
          "stop_address": "Stradbrook Rd",
          "stop_location": "Stradbrook Cottages",
          "stop_lat": "53.2925068598858",
          "stop_lon": "-6.16688424573156"
        },
        {
          "stop_num": "3164",
          "stop_address": "Stradbrook Rd",
          "stop_location": "Temple Hill",
          "stop_lat": "53.2956000271775",
          "stop_lon": "-6.16988727264522"
        },
        {
          "stop_num": "3084",
          "stop_address": "Frascati Road",
          "stop_location": "Frascati Centre",
          "stop_lat": "53.3013812515137",
          "stop_lon": "-6.18116341196197"
        },
        {
          "stop_num": "469",
          "stop_address": "Rock Road",
          "stop_location": "Mount Merrion Avenue",
          "stop_lat": "53.3028457292126",
          "stop_lon": "-6.18407213264847"
        },
        {
          "stop_num": "470",
          "stop_address": "Rock Road",
          "stop_location": "Blackrock Clinic",
          "stop_lat": "53.3056258500263",
          "stop_lon": "-6.18898110376377"
        },
        {
          "stop_num": "471",
          "stop_address": "Rock Road",
          "stop_location": "Blackrock College",
          "stop_lat": "53.3068708073446",
          "stop_lon": "-6.19105929913705"
        },
        {
          "stop_num": "472",
          "stop_address": "Rock Road",
          "stop_location": "Booterstown Ave",
          "stop_lat": "53.3078820347442",
          "stop_lon": "-6.19491826731321"
        },
        {
          "stop_num": "473",
          "stop_address": "Rock Road",
          "stop_location": "Grotto Avenue",
          "stop_lat": "53.3092405753985",
          "stop_lon": "-6.19738213927117"
        },
        {
          "stop_num": "4705",
          "stop_address": "Rock Road",
          "stop_location": "St Helen s Road",
          "stop_lat": "53.3108182690603",
          "stop_lon": "-6.20007706605352"
        },
        {
          "stop_num": "475",
          "stop_address": "Rock Road",
          "stop_location": "Bellevue Avenue",
          "stop_lat": "53.312706162538",
          "stop_lon": "-6.20188867460386"
        },
        {
          "stop_num": "476",
          "stop_address": "Rock Road",
          "stop_location": "Merrion Gates",
          "stop_lat": "53.3157515263735",
          "stop_lon": "-6.20476252273258"
        },
        {
          "stop_num": "477",
          "stop_address": "Merrion Road",
          "stop_location": "Estate Avenue",
          "stop_lat": "53.3168630546851",
          "stop_lon": "-6.20695232009327"
        },
        {
          "stop_num": "478",
          "stop_address": "Merrion Road",
          "stop_location": "St. Vincent s Hospital",
          "stop_lat": "53.3181142989183",
          "stop_lon": "-6.21126782530883"
        },
        {
          "stop_num": "479",
          "stop_address": "Merrion Road",
          "stop_location": "Merrion Centre",
          "stop_lat": "53.3191439676238",
          "stop_lon": "-6.21340128669965"
        },
        {
          "stop_num": "480",
          "stop_address": "Merrion Road",
          "stop_location": "Ailesbury Road",
          "stop_lat": "53.32084997999",
          "stop_lon": "-6.21628720536765"
        },
        {
          "stop_num": "481",
          "stop_address": "Merrion Road",
          "stop_location": "Merlyn Road",
          "stop_lat": "53.3223446397574",
          "stop_lon": "-6.21826644297952"
        },
        {
          "stop_num": "482",
          "stop_address": "Merrion Road",
          "stop_location": "Shrewsbury Road",
          "stop_lat": "53.3247277780876",
          "stop_lon": "-6.22196529496766"
        },
        {
          "stop_num": "483",
          "stop_address": "Merrion Road",
          "stop_location": "Simmonscourt Road",
          "stop_lat": "53.3259441074967",
          "stop_lon": "-6.22397148052323"
        },
        {
          "stop_num": "485",
          "stop_address": "Ballsbridge RDS",
          "stop_location": "Ballsbridge RDS",
          "stop_lat": "53.3282515101299",
          "stop_lon": "-6.22863497077614"
        },
        {
          "stop_num": "487",
          "stop_address": "American Embassy",
          "stop_location": "Pembroke Road",
          "stop_lat": "53.3308552893834",
          "stop_lon": "-6.23390230837204"
        },
        {
          "stop_num": "488",
          "stop_address": "Northumberland Rd",
          "stop_location": "Lansdowne Park",
          "stop_lat": "53.333098554632",
          "stop_lon": "-6.23607694701102"
        },
        {
          "stop_num": "489",
          "stop_address": "Northumberland Rd",
          "stop_location": "St. Mary s Road South",
          "stop_lat": "53.3349420031478",
          "stop_lon": "-6.23735231265615"
        },
        {
          "stop_num": "490",
          "stop_address": "Northumberland Rd",
          "stop_location": "Haddington Road",
          "stop_lat": "53.3365738419154",
          "stop_lon": "-6.23890680600162"
        },
        {
          "stop_num": "491",
          "stop_address": "Mount St",
          "stop_location": "Grand Canal",
          "stop_lat": "53.3378140535117",
          "stop_lon": "-6.24133351088669"
        },
        {
          "stop_num": "492",
          "stop_address": "Grattan St",
          "stop_location": "Merrion Square",
          "stop_lat": "53.3385846851446",
          "stop_lon": "-6.24361446215904"
        },
        {
          "stop_num": "493",
          "stop_address": "Merrion Sq",
          "stop_location": "Holles Street",
          "stop_lat": "53.3398534163799",
          "stop_lon": "-6.24737682273893"
        },
        {
          "stop_num": "494",
          "stop_address": "Clare Street",
          "stop_location": "Lincoln Place",
          "stop_lat": "53.341435583359",
          "stop_lon": "-6.25168225233912"
        },
        {
          "stop_num": "495",
          "stop_address": "Westland Row",
          "stop_location": "Pearse Station",
          "stop_lat": "53.3435913198155",
          "stop_lon": "-6.24974670516899"
        },
        {
          "stop_num": "400",
          "stop_address": "Shaw Street",
          "stop_location": "Pearse Street",
          "stop_lat": "53.3448491210166",
          "stop_lon": "-6.25338997292405"
        },
        {
          "stop_num": "281",
          "stop_address": "O Connell St",
          "stop_location": "Dublin Bus",
          "stop_lat": "53.3513435349612",
          "stop_lon": "-6.26111600843156"
        },
        {
          "stop_num": "6",
          "stop_address": "Parnell Square",
          "stop_location": "St. Martin s Chapel",
          "stop_lat": "53.352749335707",
          "stop_lon": "-6.26445380396429"
        },
        {
          "stop_num": "194",
          "stop_address": "Western Way",
          "stop_location": "Youth Club",
          "stop_lat": "53.3550406495542",
          "stop_lon": "-6.2699793110377"
        },
        {
          "stop_num": "195",
          "stop_address": "Phibsboro Road",
          "stop_location": "Constitution Hill",
          "stop_lat": "53.355011777879",
          "stop_lon": "-6.27357097973092"
        },
        {
          "stop_num": "196",
          "stop_address": "Phibsboro Road",
          "stop_location": "Broadstone Depot",
          "stop_lat": "53.356883899293",
          "stop_lon": "-6.27375070406949"
        },
        {
          "stop_num": "197",
          "stop_address": "Phibsboro Road",
          "stop_location": "Monck Place",
          "stop_lat": "53.3589526316143",
          "stop_lon": "-6.27323137351168"
        },
        {
          "stop_num": "198",
          "stop_address": "Phibsboro Road",
          "stop_location": "Phibsboro Shopping Centre",
          "stop_lat": "53.361625382881",
          "stop_lon": "-6.27283781041656"
        },
        {
          "stop_num": "199",
          "stop_address": "Phibsboro Road",
          "stop_location": "Munster Street",
          "stop_lat": "53.3636218115005",
          "stop_lon": "-6.27229124622515"
        },
        {
          "stop_num": "200",
          "stop_address": "Prospect Way",
          "stop_location": "Prospect Avenue",
          "stop_lat": "53.3674226926335",
          "stop_lon": "-6.27159644393797"
        },
        {
          "stop_num": "201",
          "stop_address": "Botanic Rd",
          "stop_location": "St. Teresa s Place",
          "stop_lat": "53.3682910986623",
          "stop_lon": "-6.27011862691076"
        },
        {
          "stop_num": "148",
          "stop_address": "Mobhi Road",
          "stop_location": "Botanic Road",
          "stop_lat": "53.3706701663492",
          "stop_lon": "-6.2680685070582"
        },
        {
          "stop_num": "149",
          "stop_address": "Mobhi Road",
          "stop_location": "St. Mobhi Drive",
          "stop_lat": "53.3731385872581",
          "stop_lon": "-6.26598446613774"
        },
        {
          "stop_num": "150",
          "stop_address": "Mobhi Road",
          "stop_location": "Home Farm Road",
          "stop_lat": "53.3756588461887",
          "stop_lon": "-6.26499528302818"
        },
        {
          "stop_num": "27",
          "stop_address": "Ballymun Road",
          "stop_location": "Griffith Avenue",
          "stop_lat": "53.3794389600131",
          "stop_lon": "-6.26658526125999"
        },
        {
          "stop_num": "28",
          "stop_address": "Ballymun Road",
          "stop_location": "Glasnevin Tennis Club",
          "stop_lat": "53.3815786376305",
          "stop_lon": "-6.26600227077734"
        },
        {
          "stop_num": "29",
          "stop_address": "Ballymun Road",
          "stop_location": "St. Canice s Road",
          "stop_lat": "53.3834882529482",
          "stop_lon": "-6.26566910125412"
        },
        {
          "stop_num": "4680",
          "stop_address": "Ballymun Road",
          "stop_location": "DCU",
          "stop_lat": "53.3849664763564",
          "stop_lon": "-6.26533840628634"
        },
        {
          "stop_num": "90",
          "stop_address": "Ballymun Road",
          "stop_location": "St. Pappin s Road",
          "stop_lat": "53.3863855316762",
          "stop_lon": "-6.26526567275517"
        },
        {
          "stop_num": "91",
          "stop_address": "Ballymun Road",
          "stop_location": "Glasnevin Avenue",
          "stop_lat": "53.3884278896508",
          "stop_lon": "-6.26540814207678"
        },
        {
          "stop_num": "92",
          "stop_address": "Ballymun Road",
          "stop_location": "Ballymun Library",
          "stop_lat": "53.3898373340536",
          "stop_lon": "-6.264674240361"
        },
        {
          "stop_num": "93",
          "stop_address": "Ballymun Road",
          "stop_location": "Shanliss Road",
          "stop_lat": "53.3923014677522",
          "stop_lon": "-6.26415297561009"
        },
        {
          "stop_num": "94",
          "stop_address": "Ballymun Road",
          "stop_location": "Silloge Road",
          "stop_lat": "53.396034762414",
          "stop_lon": "-6.26437695995443"
        },
        {
          "stop_num": "126",
          "stop_address": "Ballymun Road",
          "stop_location": "Nursing Home",
          "stop_lat": "53.3990954666878",
          "stop_lon": "-6.2640869605604"
        },
        {
          "stop_num": "6182",
          "stop_address": "Ballymun Road",
          "stop_location": "Santry Cross",
          "stop_lat": "53.4022507542177",
          "stop_lon": "-6.26535718879144"
        },
        {
          "stop_num": "322",
          "stop_address": "Ballymun Road",
          "stop_location": "Gulliver s Retail Park",
          "stop_lat": "53.4042549924669",
          "stop_lon": "-6.26535084532181"
        },
        {
          "stop_num": "323",
          "stop_address": "Ballymun Road",
          "stop_location": "Silloge Golf Club",
          "stop_lat": "53.4129298606578",
          "stop_lon": "-6.26544910096627"
        },
        {
          "stop_num": "332",
          "stop_address": "Harristown",
          "stop_location": "Bus Garage",
          "stop_lat": "53.4173526533912",
          "stop_lon": "-6.27853875647111"
        }
      ]
    },
    "id": "43103d87-f92e-4a6c-85c7-99e71057422d",
    "priority": 0,
    "timeToLive": {
      "unlimited": true
    },
    "times": {
      "unlimited": true
    }
  },
  {
    "httpRequest": {
      "method": "GET",
      "path": "/api/route/matchingRoute"
    },
    "httpResponse": {
      "body": [
        {
          "route_num": "145",
          "stops": [
            {
              "stop_lat": "53.3466404491063",
              "stop_lon": "-6.29206850269704",
              "stop_name": "1",
              "stop_num": "60-145-b12-1.329.O"
            },
            {
              "stop_lat": "53.3463236826931",
              "stop_lon": "-6.29191594657861",
              "stop_name": "2",
              "stop_num": "60-145-b12-1.329.O"
            },
            {
              "stop_lat": "53.3462413319414",
              "stop_lon": "-6.29181409971013",
              "stop_name": "3",
              "stop_num": "60-145-b12-1.329.O"
            },
            {
              "stop_lat": "53.3463275073403",
              "stop_lon": "-6.2915553158463",
              "stop_name": "4",
              "stop_num": "60-145-b12-1.329.O"
            },
            {
              "stop_lat": "53.3463715621602",
              "stop_lon": "-6.29149347450709",
              "stop_name": "5",
              "stop_num": "60-145-b12-1.329.O"
            },
            {
              "stop_lat": "53.3468617535323",
              "stop_lon": "-6.29120351025909",
              "stop_name": "6",
              "stop_num": "60-145-b12-1.329.O"
            },
            {
              "stop_lat": "53.3474928752602",
              "stop_lon": "-6.29071263725467",
              "stop_name": "7",
              "stop_num": "60-145-b12-1.329.O"
            },
            {
              "stop_lat": "53.3474455948738",
              "stop_lon": "-6.29054930552597",
              "stop_name": "8",
              "stop_num": "60-145-b12-1.329.O"
            },
            {
              "stop_lat": "53.3472626567651",
              "stop_lon": "-6.28970047151301",
              "stop_name": "9",
              "stop_num": "60-145-b12-1.329.O"
            },
            {
              "stop_lat": "53.3471624964673",
              "stop_lon": "-6.28898351112604",
              "stop_name": "10",
              "stop_num": "60-145-b12-1.329.O"
            },
            {
              "stop_lat": "53.3471295192357",
              "stop_lon": "-6.28856426627463",
              "stop_name": "11",
              "stop_num": "60-145-b12-1.329.O"
            },
            {
              "stop_lat": "53.3470197882093",
              "stop_lon": "-6.28467843934665",
              "stop_name": "12",
              "stop_num": "60-145-b12-1.329.O"
            },
            {
              "stop_lat": "53.3469834710839",
              "stop_lon": "-6.28340318407353",
              "stop_name": "13",
              "stop_num": "60-145-b12-1.329.O"
            },
            {
              "stop_lat": "53.346713388989",
              "stop_lon": "-6.28087564439688",
              "stop_name": "14",
              "stop_num": "60-145-b12-1.329.O"
            },
            {
              "stop_lat": "53.3466427210045",
              "stop_lon": "-6.28033776629839",
              "stop_name": "15",
              "stop_num": "60-145-b12-1.329.O"
            },
            {
              "stop_lat": "53.3462556964355",
              "stop_lon": "-6.27843079532262",
              "stop_name": "16",
              "stop_num": "60-145-b12-1.329.O"
            },
            {
              "stop_lat": "53.3458561890928",
              "stop_lon": "-6.27628404536772",
              "stop_name": "17",
              "stop_num": "60-145-b12-1.329.O"
            },
            {
              "stop_lat": "53.345833017944",
              "stop_lon": "-6.27592450569217",
              "stop_name": "18",
              "stop_num": "60-145-b12-1.329.O"
            },
            {
              "stop_lat": "53.34570213737",
              "stop_lon": "-6.27495350484753",
              "stop_name": "19",
              "stop_num": "60-145-b12-1.329.O"
            },
            {
              "stop_lat": "53.3455453219312",
              "stop_lon": "-6.27281202280554",
              "stop_name": "20",
              "stop_num": "60-145-b12-1.329.O"
            },
            {
              "stop_lat": "53.3455394539696",
              "stop_lon": "-6.27240672878141",
              "stop_name": "21",
              "stop_num": "60-145-b12-1.329.O"
            },
            {
              "stop_lat": "53.3456210880155",
              "stop_lon": "-6.27121687115839",
              "stop_name": "22",
              "stop_num": "60-145-b12-1.329.O"
            },
            {
              "stop_lat": "53.3459699101486",
              "stop_lon": "-6.26861934548463",
              "stop_name": "23",
              "stop_num": "60-145-b12-1.329.O"
            },
            {
              "stop_lat": "53.3461036592085",
              "stop_lon": "-6.26730719547513",
              "stop_name": "24",
              "stop_num": "60-145-b12-1.329.O"
            },
            {
              "stop_lat": "53.3461696761036",
              "stop_lon": "-6.26628316426139",
              "stop_name": "25",
              "stop_num": "60-145-b12-1.329.O"
            },
            {
              "stop_lat": "53.3463571089106",
              "stop_lon": "-6.26433798101895",
              "stop_name": "26",
              "stop_num": "60-145-b12-1.329.O"
            },
            {
              "stop_lat": "53.3470153659903",
              "stop_lon": "-6.26139731688271",
              "stop_name": "27",
              "stop_num": "60-145-b12-1.329.O"
            },
            {
              "stop_lat": "53.3473278150521",
              "stop_lon": "-6.26001775158859",
              "stop_name": "28",
              "stop_num": "60-145-b12-1.329.O"
            },
            {
              "stop_lat": "53.347584378647",
              "stop_lon": "-6.25912109729489",
              "stop_name": "29",
              "stop_num": "60-145-b12-1.329.O"
            },
            {
              "stop_lat": "53.3469038798236",
              "stop_lon": "-6.25868320047544",
              "stop_name": "30",
              "stop_num": "60-145-b12-1.329.O"
            },
            {
              "stop_lat": "53.3467855701351",
              "stop_lon": "-6.25858288151398",
              "stop_name": "31",
              "stop_num": "60-145-b12-1.329.O"
            },
            {
              "stop_lat": "53.3465202491463",
              "stop_lon": "-6.25826325481649",
              "stop_name": "32",
              "stop_num": "60-145-b12-1.329.O"
            },
            {
              "stop_lat": "53.3459326388213",
              "stop_lon": "-6.25741605855342",
              "stop_name": "33",
              "stop_num": "60-145-b12-1.329.O"
            },
            {
              "stop_lat": "53.3458506976735",
              "stop_lon": "-6.25734430152318",
              "stop_name": "34",
              "stop_num": "60-145-b12-1.329.O"
            },
            {
              "stop_lat": "53.3457339216984",
              "stop_lon": "-6.25734906454796",
              "stop_name": "35",
              "stop_num": "60-145-b12-1.329.O"
            },
            {
              "stop_lat": "53.3456896656071",
              "stop_lon": "-6.25739592893286",
              "stop_name": "36",
              "stop_num": "60-145-b12-1.329.O"
            },
            {
              "stop_lat": "53.3453535844656",
              "stop_lon": "-6.25838591316961",
              "stop_name": "37",
              "stop_num": "60-145-b12-1.329.O"
            },
            {
              "stop_lat": "53.3450475125197",
              "stop_lon": "-6.25896913167791",
              "stop_name": "38",
              "stop_num": "60-145-b12-1.329.O"
            },
            {
              "stop_lat": "53.3448709234341",
              "stop_lon": "-6.25918659999473",
              "stop_name": "39",
              "stop_num": "60-145-b12-1.329.O"
            },
            {
              "stop_lat": "53.3444625335271",
              "stop_lon": "-6.25953366411395",
              "stop_name": "40",
              "stop_num": "60-145-b12-1.329.O"
            },
            {
              "stop_lat": "53.3440806579666",
              "stop_lon": "-6.25923381640691",
              "stop_name": "41",
              "stop_num": "60-145-b12-1.329.O"
            },
            {
              "stop_lat": "53.3439903921541",
              "stop_lon": "-6.25920745559093",
              "stop_name": "42",
              "stop_num": "60-145-b12-1.329.O"
            },
            {
              "stop_lat": "53.3437206897675",
              "stop_lon": "-6.2592034245016",
              "stop_name": "43",
              "stop_num": "60-145-b12-1.329.O"
            },
            {
              "stop_lat": "53.3435239446494",
              "stop_lon": "-6.25927151606355",
              "stop_name": "44",
              "stop_num": "60-145-b12-1.329.O"
            },
            {
              "stop_lat": "53.3433981857288",
              "stop_lon": "-6.25927663936881",
              "stop_name": "45",
              "stop_num": "60-145-b12-1.329.O"
            },
            {
              "stop_lat": "53.3432616919503",
              "stop_lon": "-6.25916204871902",
              "stop_name": "46",
              "stop_num": "60-145-b12-1.329.O"
            },
            {
              "stop_lat": "53.3432060430792",
              "stop_lon": "-6.25904416484425",
              "stop_name": "47",
              "stop_num": "60-145-b12-1.329.O"
            },
            {
              "stop_lat": "53.3425529067492",
              "stop_lon": "-6.25617217451087",
              "stop_name": "48",
              "stop_num": "60-145-b12-1.329.O"
            },
            {
              "stop_lat": "53.3423028953246",
              "stop_lon": "-6.2550559842903",
              "stop_name": "49",
              "stop_num": "60-145-b12-1.329.O"
            },
            {
              "stop_lat": "53.3421698911555",
              "stop_lon": "-6.25456580411832",
              "stop_name": "50",
              "stop_num": "60-145-b12-1.329.O"
            },
            {
              "stop_lat": "53.3408496633297",
              "stop_lon": "-6.25525048870062",
              "stop_name": "51",
              "stop_num": "60-145-b12-1.329.O"
            },
            {
              "stop_lat": "53.3399498657418",
              "stop_lon": "-6.2557978293956",
              "stop_name": "52",
              "stop_num": "60-145-b12-1.329.O"
            },
            {
              "stop_lat": "53.3391756047812",
              "stop_lon": "-6.25632500702549",
              "stop_name": "53",
              "stop_num": "60-145-b12-1.329.O"
            },
            {
              "stop_lat": "53.3388559538039",
              "stop_lon": "-6.25659334438586",
              "stop_name": "54",
              "stop_num": "60-145-b12-1.329.O"
            },
            {
              "stop_lat": "53.3387209815838",
              "stop_lon": "-6.25596812331344",
              "stop_name": "55",
              "stop_num": "60-145-b12-1.329.O"
            },
            {
              "stop_lat": "53.3386287402985",
              "stop_lon": "-6.25580669749724",
              "stop_name": "56",
              "stop_num": "60-145-b12-1.329.O"
            },
            {
              "stop_lat": "53.3384733999611",
              "stop_lon": "-6.25563283063203",
              "stop_name": "57",
              "stop_num": "60-145-b12-1.329.O"
            },
            {
              "stop_lat": "53.3383025078774",
              "stop_lon": "-6.2556247887166",
              "stop_name": "58",
              "stop_num": "60-145-b12-1.329.O"
            },
            {
              "stop_lat": "53.3381598807582",
              "stop_lon": "-6.25570569588059",
              "stop_name": "59",
              "stop_num": "60-145-b12-1.329.O"
            },
            {
              "stop_lat": "53.337289222227",
              "stop_lon": "-6.25640197041878",
              "stop_name": "60",
              "stop_num": "60-145-b12-1.329.O"
            },
            {
              "stop_lat": "53.3364810002228",
              "stop_lon": "-6.25706563690748",
              "stop_name": "61",
              "stop_num": "60-145-b12-1.329.O"
            },
            {
              "stop_lat": "53.3362941158573",
              "stop_lon": "-6.25719338976881",
              "stop_name": "62",
              "stop_num": "60-145-b12-1.329.O"
            },
            {
              "stop_lat": "53.336213270828",
              "stop_lon": "-6.25719668639006",
              "stop_name": "63",
              "stop_num": "60-145-b12-1.329.O"
            },
            {
              "stop_lat": "53.3360864156512",
              "stop_lon": "-6.25712677720053",
              "stop_name": "64",
              "stop_num": "60-145-b12-1.329.O"
            },
            {
              "stop_lat": "53.3358202138433",
              "stop_lon": "-6.25674720874598",
              "stop_name": "65",
              "stop_num": "60-145-b12-1.329.O"
            },
            {
              "stop_lat": "53.3354186111354",
              "stop_lon": "-6.25632812020553",
              "stop_name": "66",
              "stop_num": "60-145-b12-1.329.O"
            },
            {
              "stop_lat": "53.3346980019744",
              "stop_lon": "-6.2556067225091",
              "stop_name": "67",
              "stop_num": "60-145-b12-1.329.O"
            },
            {
              "stop_lat": "53.3343960838355",
              "stop_lon": "-6.25524364932377",
              "stop_name": "68",
              "stop_num": "60-145-b12-1.329.O"
            },
            {
              "stop_lat": "53.3334193392437",
              "stop_lon": "-6.25421742149017",
              "stop_name": "69",
              "stop_num": "60-145-b12-1.329.O"
            },
            {
              "stop_lat": "53.3322322466115",
              "stop_lon": "-6.25294458001983",
              "stop_name": "70",
              "stop_num": "60-145-b12-1.329.O"
            },
            {
              "stop_lat": "53.3315504065573",
              "stop_lon": "-6.25241689889836",
              "stop_name": "71",
              "stop_num": "60-145-b12-1.329.O"
            },
            {
              "stop_lat": "53.3314231089767",
              "stop_lon": "-6.25231699972668",
              "stop_name": "72",
              "stop_num": "60-145-b12-1.329.O"
            },
            {
              "stop_lat": "53.3312206511434",
              "stop_lon": "-6.25199495381448",
              "stop_name": "73",
              "stop_num": "60-145-b12-1.329.O"
            },
            {
              "stop_lat": "53.33117724294",
              "stop_lon": "-6.25148622989503",
              "stop_name": "74",
              "stop_num": "60-145-b12-1.329.O"
            },
            {
              "stop_lat": "53.3311038411686",
              "stop_lon": "-6.25138412970301",
              "stop_name": "75",
              "stop_num": "60-145-b12-1.329.O"
            },
            {
              "stop_lat": "53.3308225159476",
              "stop_lon": "-6.25120044816153",
              "stop_name": "76",
              "stop_num": "60-145-b12-1.329.O"
            },
            {
              "stop_lat": "53.3306761518566",
              "stop_lon": "-6.25102626178426",
              "stop_name": "77",
              "stop_num": "60-145-b12-1.329.O"
            },
            {
              "stop_lat": "53.3296309426544",
              "stop_lon": "-6.24901208670741",
              "stop_name": "78",
              "stop_num": "60-145-b12-1.329.O"
            },
            {
              "stop_lat": "53.3293164971423",
              "stop_lon": "-6.24840939073252",
              "stop_name": "79",
              "stop_num": "60-145-b12-1.329.O"
            },
            {
              "stop_lat": "53.3290561655278",
              "stop_lon": "-6.24781949954174",
              "stop_name": "80",
              "stop_num": "60-145-b12-1.329.O"
            },
            {
              "stop_lat": "53.3285186309328",
              "stop_lon": "-6.24671549914969",
              "stop_name": "81",
              "stop_num": "60-145-b12-1.329.O"
            },
            {
              "stop_lat": "53.3284059856902",
              "stop_lon": "-6.24638981712413",
              "stop_name": "82",
              "stop_num": "60-145-b12-1.329.O"
            },
            {
              "stop_lat": "53.3280875550497",
              "stop_lon": "-6.24551707593283",
              "stop_name": "83",
              "stop_num": "60-145-b12-1.329.O"
            },
            {
              "stop_lat": "53.3280862308752",
              "stop_lon": "-6.24542704865704",
              "stop_name": "84",
              "stop_num": "60-145-b12-1.329.O"
            },
            {
              "stop_lat": "53.327964378683",
              "stop_lon": "-6.24508673759574",
              "stop_name": "85",
              "stop_num": "60-145-b12-1.329.O"
            },
            {
              "stop_lat": "53.3277040308986",
              "stop_lon": "-6.24449688548202",
              "stop_name": "86",
              "stop_num": "60-145-b12-1.329.O"
            },
            {
              "stop_lat": "53.3274927904883",
              "stop_lon": "-6.24419027793743",
              "stop_name": "87",
              "stop_num": "60-145-b12-1.329.O"
            },
            {
              "stop_lat": "53.3274292487914",
              "stop_lon": "-6.24414784736028",
              "stop_name": "88",
              "stop_num": "60-145-b12-1.329.O"
            },
            {
              "stop_lat": "53.3263388720881",
              "stop_lon": "-6.24273636646622",
              "stop_name": "89",
              "stop_num": "60-145-b12-1.329.O"
            },
            {
              "stop_lat": "53.3240552746958",
              "stop_lon": "-6.23964763167741",
              "stop_name": "90",
              "stop_num": "60-145-b12-1.329.O"
            },
            {
              "stop_lat": "53.3234877163578",
              "stop_lon": "-6.23895042128719",
              "stop_name": "91",
              "stop_num": "60-145-b12-1.329.O"
            },
            {
              "stop_lat": "53.3226348199283",
              "stop_lon": "-6.23779962225068",
              "stop_name": "92",
              "stop_num": "60-145-b12-1.329.O"
            },
            {
              "stop_lat": "53.3223863017417",
              "stop_lon": "-6.23740455004916",
              "stop_name": "93",
              "stop_num": "60-145-b12-1.329.O"
            },
            {
              "stop_lat": "53.3222195135823",
              "stop_lon": "-6.23706615902805",
              "stop_name": "94",
              "stop_num": "60-145-b12-1.329.O"
            },
            {
              "stop_lat": "53.3221331252564",
              "stop_lon": "-6.23669443227024",
              "stop_name": "95",
              "stop_num": "60-145-b12-1.329.O"
            },
            {
              "stop_lat": "53.3220719091955",
              "stop_lon": "-6.23620157668348",
              "stop_name": "96",
              "stop_num": "60-145-b12-1.329.O"
            },
            {
              "stop_lat": "53.3219967197128",
              "stop_lon": "-6.23597950574442",
              "stop_name": "97",
              "stop_num": "60-145-b12-1.329.O"
            },
            {
              "stop_lat": "53.3218858209215",
              "stop_lon": "-6.2357739202924",
              "stop_name": "98",
              "stop_num": "60-145-b12-1.329.O"
            },
            {
              "stop_lat": "53.3202879717172",
              "stop_lon": "-6.23348312986016",
              "stop_name": "99",
              "stop_num": "60-145-b12-1.329.O"
            },
            {
              "stop_lat": "53.3197203781824",
              "stop_lon": "-6.23278606239085",
              "stop_name": "100",
              "stop_num": "60-145-b12-1.329.O"
            },
            {
              "stop_lat": "53.3191790616643",
              "stop_lon": "-6.23204289539884",
              "stop_name": "101",
              "stop_num": "60-145-b12-1.329.O"
            },
            {
              "stop_lat": "53.3191220523437",
              "stop_lon": "-6.23183510536475",
              "stop_name": "102",
              "stop_num": "60-145-b12-1.329.O"
            },
            {
              "stop_lat": "53.3182868316393",
              "stop_lon": "-6.23066882107102",
              "stop_name": "103",
              "stop_num": "60-145-b12-1.329.O"
            },
            {
              "stop_lat": "53.316057047869",
              "stop_lon": "-6.22759407627759",
              "stop_name": "104",
              "stop_num": "60-145-b12-1.329.O"
            },
            {
              "stop_lat": "53.3154786540573",
              "stop_lon": "-6.22677752800523",
              "stop_name": "105",
              "stop_num": "60-145-b12-1.329.O"
            },
            {
              "stop_lat": "53.3150266813922",
              "stop_lon": "-6.22600078527134",
              "stop_name": "106",
              "stop_num": "60-145-b12-1.329.O"
            },
            {
              "stop_lat": "53.3146068396796",
              "stop_lon": "-6.22496757397345",
              "stop_name": "107",
              "stop_num": "60-145-b12-1.329.O"
            },
            {
              "stop_lat": "53.3144371141714",
              "stop_lon": "-6.22443429844667",
              "stop_name": "108",
              "stop_num": "60-145-b12-1.329.O"
            },
            {
              "stop_lat": "53.3142581802857",
              "stop_lon": "-6.22388640065767",
              "stop_name": "109",
              "stop_num": "60-145-b12-1.329.O"
            },
            {
              "stop_lat": "53.3140994435137",
              "stop_lon": "-6.22348775590504",
              "stop_name": "110",
              "stop_num": "60-145-b12-1.329.O"
            },
            {
              "stop_lat": "53.3138675033771",
              "stop_lon": "-6.22300210308547",
              "stop_name": "111",
              "stop_num": "60-145-b12-1.329.O"
            },
            {
              "stop_lat": "53.3136184901496",
              "stop_lon": "-6.22257719923552",
              "stop_name": "112",
              "stop_num": "60-145-b12-1.329.O"
            },
            {
              "stop_lat": "53.3133524044736",
              "stop_lon": "-6.22221304378111",
              "stop_name": "113",
              "stop_num": "60-145-b12-1.329.O"
            },
            {
              "stop_lat": "53.3130508343714",
              "stop_lon": "-6.2218803846188",
              "stop_name": "114",
              "stop_num": "60-145-b12-1.329.O"
            },
            {
              "stop_lat": "53.3122862275688",
              "stop_lon": "-6.22123680255006",
              "stop_name": "115",
              "stop_num": "60-145-b12-1.329.O"
            },
            {
              "stop_lat": "53.3116498358151",
              "stop_lon": "-6.22075299659043",
              "stop_name": "116",
              "stop_num": "60-145-b12-1.329.O"
            },
            {
              "stop_lat": "53.3111126988337",
              "stop_lon": "-6.22029509085019",
              "stop_name": "117",
              "stop_num": "60-145-b12-1.329.O"
            },
            {
              "stop_lat": "53.3106276649658",
              "stop_lon": "-6.21971496801514",
              "stop_name": "118",
              "stop_num": "60-145-b12-1.329.O"
            },
            {
              "stop_lat": "53.3103126265649",
              "stop_lon": "-6.21908275921759",
              "stop_name": "119",
              "stop_num": "60-145-b12-1.329.O"
            },
            {
              "stop_lat": "53.3095877824974",
              "stop_lon": "-6.21749215927668",
              "stop_name": "120",
              "stop_num": "60-145-b12-1.329.O"
            },
            {
              "stop_lat": "53.3088224912552",
              "stop_lon": "-6.21620343745046",
              "stop_name": "121",
              "stop_num": "60-145-b12-1.329.O"
            },
            {
              "stop_lat": "53.3077178697302",
              "stop_lon": "-6.21446371699655",
              "stop_name": "122",
              "stop_num": "60-145-b12-1.329.O"
            },
            {
              "stop_lat": "53.3074517598679",
              "stop_lon": "-6.21409966195722",
              "stop_name": "123",
              "stop_num": "60-145-b12-1.329.O"
            },
            {
              "stop_lat": "53.3065676360621",
              "stop_lon": "-6.21268097224682",
              "stop_name": "124",
              "stop_num": "60-145-b12-1.329.O"
            },
            {
              "stop_lat": "53.3055478569223",
              "stop_lon": "-6.21120798851181",
              "stop_name": "125",
              "stop_num": "60-145-b12-1.329.O"
            },
            {
              "stop_lat": "53.3032697407857",
              "stop_lon": "-6.20794210846196",
              "stop_name": "126",
              "stop_num": "60-145-b12-1.329.O"
            },
            {
              "stop_lat": "53.3027844228651",
              "stop_lon": "-6.20734723596527",
              "stop_name": "127",
              "stop_num": "60-145-b12-1.329.O"
            },
            {
              "stop_lat": "53.3023276282015",
              "stop_lon": "-6.20685621403784",
              "stop_name": "128",
              "stop_num": "60-145-b12-1.329.O"
            },
            {
              "stop_lat": "53.3015359948496",
              "stop_lon": "-6.20621418875312",
              "stop_name": "129",
              "stop_num": "60-145-b12-1.329.O"
            },
            {
              "stop_lat": "53.2988808563116",
              "stop_lon": "-6.20478012167534",
              "stop_name": "130",
              "stop_num": "60-145-b12-1.329.O"
            },
            {
              "stop_lat": "53.2977034126763",
              "stop_lon": "-6.20418437956158",
              "stop_name": "131",
              "stop_num": "60-145-b12-1.329.O"
            },
            {
              "stop_lat": "53.296972210508",
              "stop_lon": "-6.20397501494862",
              "stop_name": "132",
              "stop_num": "60-145-b12-1.329.O"
            },
            {
              "stop_lat": "53.2962791966637",
              "stop_lon": "-6.20391407991611",
              "stop_name": "133",
              "stop_num": "60-145-b12-1.329.O"
            },
            {
              "stop_lat": "53.2959811905721",
              "stop_lon": "-6.2038215680554",
              "stop_name": "134",
              "stop_num": "60-145-b12-1.329.O"
            },
            {
              "stop_lat": "53.2957918787954",
              "stop_lon": "-6.20378450535408",
              "stop_name": "135",
              "stop_num": "60-145-b12-1.329.O"
            },
            {
              "stop_lat": "53.2953568752114",
              "stop_lon": "-6.20354772260348",
              "stop_name": "136",
              "stop_num": "60-145-b12-1.329.O"
            },
            {
              "stop_lat": "53.2950027144081",
              "stop_lon": "-6.20330755115739",
              "stop_name": "137",
              "stop_num": "60-145-b12-1.329.O"
            },
            {
              "stop_lat": "53.2946386668141",
              "stop_lon": "-6.20300779080964",
              "stop_name": "138",
              "stop_num": "60-145-b12-1.329.O"
            },
            {
              "stop_lat": "53.2941010116409",
              "stop_lon": "-6.2025203018403",
              "stop_name": "139",
              "stop_num": "60-145-b12-1.329.O"
            },
            {
              "stop_lat": "53.2936987713702",
              "stop_lon": "-6.20207214198237",
              "stop_name": "140",
              "stop_num": "60-145-b12-1.329.O"
            },
            {
              "stop_lat": "53.2934782159007",
              "stop_lon": "-6.20175137145878",
              "stop_name": "141",
              "stop_num": "60-145-b12-1.329.O"
            },
            {
              "stop_lat": "53.2931471549625",
              "stop_lon": "-6.20125522991841",
              "stop_name": "142",
              "stop_num": "60-145-b12-1.329.O"
            },
            {
              "stop_lat": "53.2905829803729",
              "stop_lon": "-6.19692280670966",
              "stop_name": "143",
              "stop_num": "60-145-b12-1.329.O"
            },
            {
              "stop_lat": "53.2901779984959",
              "stop_lon": "-6.19629484565541",
              "stop_name": "144",
              "stop_num": "60-145-b12-1.329.O"
            },
            {
              "stop_lat": "53.2897013798104",
              "stop_lon": "-6.19568491577634",
              "stop_name": "145",
              "stop_num": "60-145-b12-1.329.O"
            },
            {
              "stop_lat": "53.2890814911079",
              "stop_lon": "-6.19511103944872",
              "stop_name": "146",
              "stop_num": "60-145-b12-1.329.O"
            },
            {
              "stop_lat": "53.2889453913284",
              "stop_lon": "-6.19502677718711",
              "stop_name": "147",
              "stop_num": "60-145-b12-1.329.O"
            },
            {
              "stop_lat": "53.2883827995646",
              "stop_lon": "-6.19467550071934",
              "stop_name": "148",
              "stop_num": "60-145-b12-1.329.O"
            },
            {
              "stop_lat": "53.2880299833903",
              "stop_lon": "-6.19452538142435",
              "stop_name": "149",
              "stop_num": "60-145-b12-1.329.O"
            },
            {
              "stop_lat": "53.2876688654794",
              "stop_lon": "-6.19442061325933",
              "stop_name": "150",
              "stop_num": "60-145-b12-1.329.O"
            },
            {
              "stop_lat": "53.2872904633909",
              "stop_lon": "-6.19436157394766",
              "stop_name": "151",
              "stop_num": "60-145-b12-1.329.O"
            },
            {
              "stop_lat": "53.2868231437797",
              "stop_lon": "-6.19436628251962",
              "stop_name": "152",
              "stop_num": "60-145-b12-1.329.O"
            },
            {
              "stop_lat": "53.2853264622556",
              "stop_lon": "-6.1946543782042",
              "stop_name": "153",
              "stop_num": "60-145-b12-1.329.O"
            },
            {
              "stop_lat": "53.2850387935528",
              "stop_lon": "-6.19465150838554",
              "stop_name": "154",
              "stop_num": "60-145-b12-1.329.O"
            },
            {
              "stop_lat": "53.2847681820904",
              "stop_lon": "-6.19458792530077",
              "stop_name": "155",
              "stop_num": "60-145-b12-1.329.O"
            },
            {
              "stop_lat": "53.2841710208059",
              "stop_lon": "-6.19432813526234",
              "stop_name": "156",
              "stop_num": "60-145-b12-1.329.O"
            },
            {
              "stop_lat": "53.2825760142573",
              "stop_lon": "-6.19346553034294",
              "stop_name": "157",
              "stop_num": "60-145-b12-1.329.O"
            },
            {
              "stop_lat": "53.2822218337306",
              "stop_lon": "-6.19322551197783",
              "stop_name": "158",
              "stop_num": "60-145-b12-1.329.O"
            },
            {
              "stop_lat": "53.2820756143491",
              "stop_lon": "-6.19306670773409",
              "stop_name": "159",
              "stop_num": "60-145-b12-1.329.O"
            },
            {
              "stop_lat": "53.2817560001271",
              "stop_lon": "-6.19273525183461",
              "stop_name": "160",
              "stop_num": "60-145-b12-1.329.O"
            },
            {
              "stop_lat": "53.2815165462406",
              "stop_lon": "-6.19235542512088",
              "stop_name": "161",
              "stop_num": "60-145-b12-1.329.O"
            },
            {
              "stop_lat": "53.2812103492148",
              "stop_lon": "-6.1917234666259",
              "stop_name": "162",
              "stop_num": "60-145-b12-1.329.O"
            },
            {
              "stop_lat": "53.2806207980684",
              "stop_lon": "-6.19018866378372",
              "stop_name": "163",
              "stop_num": "60-145-b12-1.329.O"
            },
            {
              "stop_lat": "53.2801437991547",
              "stop_lon": "-6.18896407750194",
              "stop_name": "164",
              "stop_num": "60-145-b12-1.329.O"
            },
            {
              "stop_lat": "53.2781380133584",
              "stop_lon": "-6.18414512896505",
              "stop_name": "165",
              "stop_num": "60-145-b12-1.329.O"
            },
            {
              "stop_lat": "53.2775978473862",
              "stop_lon": "-6.18290836303246",
              "stop_name": "166",
              "stop_num": "60-145-b12-1.329.O"
            },
            {
              "stop_lat": "53.2754735676226",
              "stop_lon": "-6.1791746792991",
              "stop_name": "167",
              "stop_num": "60-145-b12-1.329.O"
            },
            {
              "stop_lat": "53.2751318299462",
              "stop_lon": "-6.17857440359748",
              "stop_name": "168",
              "stop_num": "60-145-b12-1.329.O"
            },
            {
              "stop_lat": "53.2747295518398",
              "stop_lon": "-6.1775418561776",
              "stop_name": "169",
              "stop_num": "60-145-b12-1.329.O"
            },
            {
              "stop_lat": "53.2745004532625",
              "stop_lon": "-6.17666690031587",
              "stop_name": "170",
              "stop_num": "60-145-b12-1.329.O"
            },
            {
              "stop_lat": "53.2741431088682",
              "stop_lon": "-6.1750476728629",
              "stop_name": "171",
              "stop_num": "60-145-b12-1.329.O"
            },
            {
              "stop_lat": "53.2738218723803",
              "stop_lon": "-6.17402672178311",
              "stop_name": "172",
              "stop_num": "60-145-b12-1.329.O"
            },
            {
              "stop_lat": "53.2736070117233",
              "stop_lon": "-6.17349607272528",
              "stop_name": "173",
              "stop_num": "60-145-b12-1.329.O"
            },
            {
              "stop_lat": "53.2732908153592",
              "stop_lon": "-6.17280481089063",
              "stop_name": "174",
              "stop_num": "60-145-b12-1.329.O"
            },
            {
              "stop_lat": "53.2727546702965",
              "stop_lon": "-6.17183805134899",
              "stop_name": "175",
              "stop_num": "60-145-b12-1.329.O"
            },
            {
              "stop_lat": "53.2724407631774",
              "stop_lon": "-6.17129666005086",
              "stop_name": "176",
              "stop_num": "60-145-b12-1.329.O"
            },
            {
              "stop_lat": "53.2720780323728",
              "stop_lon": "-6.17050246110565",
              "stop_name": "177",
              "stop_num": "60-145-b12-1.329.O"
            },
            {
              "stop_lat": "53.2714817675957",
              "stop_lon": "-6.16854872651946",
              "stop_name": "178",
              "stop_num": "60-145-b12-1.329.O"
            },
            {
              "stop_lat": "53.2713032732599",
              "stop_lon": "-6.16804656579563",
              "stop_name": "179",
              "stop_num": "60-145-b12-1.329.O"
            },
            {
              "stop_lat": "53.2711070422833",
              "stop_lon": "-6.16756016167049",
              "stop_name": "180",
              "stop_num": "60-145-b12-1.329.O"
            },
            {
              "stop_lat": "53.2705305469694",
              "stop_lon": "-6.16631036398614",
              "stop_name": "181",
              "stop_num": "60-145-b12-1.329.O"
            },
            {
              "stop_lat": "53.2684863423457",
              "stop_lon": "-6.16197495150981",
              "stop_name": "182",
              "stop_num": "60-145-b12-1.329.O"
            },
            {
              "stop_lat": "53.2680132191704",
              "stop_lon": "-6.16102072060138",
              "stop_name": "183",
              "stop_num": "60-145-b12-1.329.O"
            },
            {
              "stop_lat": "53.2676163412883",
              "stop_lon": "-6.16034809562765",
              "stop_name": "184",
              "stop_num": "60-145-b12-1.329.O"
            },
            {
              "stop_lat": "53.2672943257399",
              "stop_lon": "-6.15986716979042",
              "stop_name": "185",
              "stop_num": "60-145-b12-1.329.O"
            },
            {
              "stop_lat": "53.2662939582758",
              "stop_lon": "-6.1585308551579",
              "stop_name": "186",
              "stop_num": "60-145-b12-1.329.O"
            },
            {
              "stop_lat": "53.2658694248762",
              "stop_lon": "-6.15781449259796",
              "stop_name": "187",
              "stop_num": "60-145-b12-1.329.O"
            },
            {
              "stop_lat": "53.2623848038517",
              "stop_lon": "-6.15045391079041",
              "stop_name": "188",
              "stop_num": "60-145-b12-1.329.O"
            },
            {
              "stop_lat": "53.2623290500088",
              "stop_lon": "-6.15033639093688",
              "stop_name": "189",
              "stop_num": "60-145-b12-1.329.O"
            },
            {
              "stop_lat": "53.2618641201162",
              "stop_lon": "-6.14933709666909",
              "stop_name": "190",
              "stop_num": "60-145-b12-1.329.O"
            },
            {
              "stop_lat": "53.2615401998996",
              "stop_lon": "-6.14873647457951",
              "stop_name": "191",
              "stop_num": "60-145-b12-1.329.O"
            },
            {
              "stop_lat": "53.26111653983",
              "stop_lon": "-6.14808020998016",
              "stop_name": "192",
              "stop_num": "60-145-b12-1.329.O"
            },
            {
              "stop_lat": "53.2606396805607",
              "stop_lon": "-6.1474712284198",
              "stop_name": "193",
              "stop_num": "60-145-b12-1.329.O"
            },
            {
              "stop_lat": "53.2600103511502",
              "stop_lon": "-6.14688384296067",
              "stop_name": "194",
              "stop_num": "60-145-b12-1.329.O"
            },
            {
              "stop_lat": "53.2595830566005",
              "stop_lon": "-6.14657254259064",
              "stop_name": "195",
              "stop_num": "60-145-b12-1.329.O"
            },
            {
              "stop_lat": "53.2591110824687",
              "stop_lon": "-6.14627817045931",
              "stop_name": "196",
              "stop_num": "60-145-b12-1.329.O"
            },
            {
              "stop_lat": "53.2585960597965",
              "stop_lon": "-6.14610558265943",
              "stop_name": "197",
              "stop_num": "60-145-b12-1.329.O"
            },
            {
              "stop_lat": "53.2555089485639",
              "stop_lon": "-6.14526485797227",
              "stop_name": "198",
              "stop_num": "60-145-b12-1.329.O"
            },
            {
              "stop_lat": "53.2551196772816",
              "stop_lon": "-6.14508685410668",
              "stop_name": "199",
              "stop_num": "60-145-b12-1.329.O"
            },
            {
              "stop_lat": "53.2544016788636",
              "stop_lon": "-6.14457835531638",
              "stop_name": "200",
              "stop_num": "60-145-b12-1.329.O"
            },
            {
              "stop_lat": "53.2526885059408",
              "stop_lon": "-6.14307882635831",
              "stop_name": "201",
              "stop_num": "60-145-b12-1.329.O"
            },
            {
              "stop_lat": "53.2507113237611",
              "stop_lon": "-6.14136605872332",
              "stop_name": "202",
              "stop_num": "60-145-b12-1.329.O"
            },
            {
              "stop_lat": "53.2503639218905",
              "stop_lon": "-6.14099146781024",
              "stop_name": "203",
              "stop_num": "60-145-b12-1.329.O"
            },
            {
              "stop_lat": "53.2497421418386",
              "stop_lon": "-6.14031406826638",
              "stop_name": "204",
              "stop_num": "60-145-b12-1.329.O"
            },
            {
              "stop_lat": "53.2493567037818",
              "stop_lon": "-6.13980626795875",
              "stop_name": "205",
              "stop_num": "60-145-b12-1.329.O"
            },
            {
              "stop_lat": "53.2492804036125",
              "stop_lon": "-6.1395248400352",
              "stop_name": "206",
              "stop_num": "60-145-b12-1.329.O"
            },
            {
              "stop_lat": "53.2483776840607",
              "stop_lon": "-6.13812536349833",
              "stop_name": "207",
              "stop_num": "60-145-b12-1.329.O"
            },
            {
              "stop_lat": "53.247513687137",
              "stop_lon": "-6.13690408982685",
              "stop_name": "208",
              "stop_num": "60-145-b12-1.329.O"
            },
            {
              "stop_lat": "53.2471116752443",
              "stop_lon": "-6.13648697906041",
              "stop_name": "209",
              "stop_num": "60-145-b12-1.329.O"
            },
            {
              "stop_lat": "53.2468547842427",
              "stop_lon": "-6.13615347983535",
              "stop_name": "210",
              "stop_num": "60-145-b12-1.329.O"
            },
            {
              "stop_lat": "53.2455608644805",
              "stop_lon": "-6.13445648472269",
              "stop_name": "211",
              "stop_num": "60-145-b12-1.329.O"
            },
            {
              "stop_lat": "53.2452585874941",
              "stop_lon": "-6.13409501463124",
              "stop_name": "212",
              "stop_num": "60-145-b12-1.329.O"
            },
            {
              "stop_lat": "53.2451860256506",
              "stop_lon": "-6.13405321766541",
              "stop_name": "213",
              "stop_num": "60-145-b12-1.329.O"
            },
            {
              "stop_lat": "53.2438826886534",
              "stop_lon": "-6.1317573858568",
              "stop_name": "214",
              "stop_num": "60-145-b12-1.329.O"
            },
            {
              "stop_lat": "53.2435333790563",
              "stop_lon": "-6.13126313975082",
              "stop_name": "215",
              "stop_num": "60-145-b12-1.329.O"
            },
            {
              "stop_lat": "53.2429030326846",
              "stop_lon": "-6.13061632724746",
              "stop_name": "216",
              "stop_num": "60-145-b12-1.329.O"
            },
            {
              "stop_lat": "53.2420292211191",
              "stop_lon": "-6.12992021502375",
              "stop_name": "217",
              "stop_num": "60-145-b12-1.329.O"
            },
            {
              "stop_lat": "53.2418739373982",
              "stop_lon": "-6.12976216606955",
              "stop_name": "218",
              "stop_num": "60-145-b12-1.329.O"
            },
            {
              "stop_lat": "53.2416787289608",
              "stop_lon": "-6.12935113832733",
              "stop_name": "219",
              "stop_num": "60-145-b12-1.329.O"
            },
            {
              "stop_lat": "53.2416671611594",
              "stop_lon": "-6.12918682336548",
              "stop_name": "220",
              "stop_num": "60-145-b12-1.329.O"
            },
            {
              "stop_lat": "53.2415709910562",
              "stop_lon": "-6.12878646242976",
              "stop_name": "221",
              "stop_num": "60-145-b12-1.329.O"
            },
            {
              "stop_lat": "53.2414785818884",
              "stop_lon": "-6.12862567561609",
              "stop_name": "222",
              "stop_num": "60-145-b12-1.329.O"
            },
            {
              "stop_lat": "53.2413507136472",
              "stop_lon": "-6.12849640387513",
              "stop_name": "223",
              "stop_num": "60-145-b12-1.329.O"
            },
            {
              "stop_lat": "53.2411081918746",
              "stop_lon": "-6.12850698714899",
              "stop_name": "224",
              "stop_num": "60-145-b12-1.329.O"
            },
            {
              "stop_lat": "53.2408942628798",
              "stop_lon": "-6.12862120583458",
              "stop_name": "225",
              "stop_num": "60-145-b12-1.329.O"
            },
            {
              "stop_lat": "53.2406973578808",
              "stop_lon": "-6.12867474752999",
              "stop_name": "226",
              "stop_num": "60-145-b12-1.329.O"
            },
            {
              "stop_lat": "53.2405718409413",
              "stop_lon": "-6.12869520747392",
              "stop_name": "227",
              "stop_num": "60-145-b12-1.329.O"
            },
            {
              "stop_lat": "53.2403735252118",
              "stop_lon": "-6.12865891107814",
              "stop_name": "228",
              "stop_num": "60-145-b12-1.329.O"
            },
            {
              "stop_lat": "53.239776461682",
              "stop_lon": "-6.12841526969312",
              "stop_name": "229",
              "stop_num": "60-145-b12-1.329.O"
            },
            {
              "stop_lat": "53.2396218815233",
              "stop_lon": "-6.12830215219767",
              "stop_name": "230",
              "stop_num": "60-145-b12-1.329.O"
            },
            {
              "stop_lat": "53.2388995356016",
              "stop_lon": "-6.12809395300502",
              "stop_name": "231",
              "stop_num": "60-145-b12-1.329.O"
            },
            {
              "stop_lat": "53.2380914088895",
              "stop_lon": "-6.12757487534413",
              "stop_name": "232",
              "stop_num": "60-145-b12-1.329.O"
            },
            {
              "stop_lat": "53.2377288237439",
              "stop_lon": "-6.12738095273664",
              "stop_name": "233",
              "stop_num": "60-145-b12-1.329.O"
            },
            {
              "stop_lat": "53.2368762532512",
              "stop_lon": "-6.12689380678621",
              "stop_name": "234",
              "stop_num": "60-145-b12-1.329.O"
            },
            {
              "stop_lat": "53.23607259359",
              "stop_lon": "-6.12665923135628",
              "stop_name": "235",
              "stop_num": "60-145-b12-1.329.O"
            },
            {
              "stop_lat": "53.2358364651214",
              "stop_lon": "-6.12650474657407",
              "stop_name": "236",
              "stop_num": "60-145-b12-1.329.O"
            },
            {
              "stop_lat": "53.2355079241584",
              "stop_lon": "-6.1261895040489",
              "stop_name": "237",
              "stop_num": "60-145-b12-1.329.O"
            },
            {
              "stop_lat": "53.2351945213796",
              "stop_lon": "-6.12569382879285",
              "stop_name": "238",
              "stop_num": "60-145-b12-1.329.O"
            },
            {
              "stop_lat": "53.2349288543038",
              "stop_lon": "-6.1253758493703",
              "stop_name": "239",
              "stop_num": "60-145-b12-1.329.O"
            },
            {
              "stop_lat": "53.2343270729664",
              "stop_lon": "-6.12483286803274",
              "stop_name": "240",
              "stop_num": "60-145-b12-1.329.O"
            },
            {
              "stop_lat": "53.2336080483234",
              "stop_lon": "-6.12426506651358",
              "stop_name": "241",
              "stop_num": "60-145-b12-1.329.O"
            },
            {
              "stop_lat": "53.2333981566673",
              "stop_lon": "-6.12406451395218",
              "stop_name": "242",
              "stop_num": "60-145-b12-1.329.O"
            },
            {
              "stop_lat": "53.2332598871924",
              "stop_lon": "-6.12384585033368",
              "stop_name": "243",
              "stop_num": "60-145-b12-1.329.O"
            },
            {
              "stop_lat": "53.2333033843243",
              "stop_lon": "-6.12375406390021",
              "stop_name": "244",
              "stop_num": "60-145-b12-1.329.O"
            },
            {
              "stop_lat": "53.2333024414546",
              "stop_lon": "-6.1236941823975",
              "stop_name": "245",
              "stop_num": "60-145-b12-1.329.O"
            },
            {
              "stop_lat": "53.2332738445362",
              "stop_lon": "-6.12359056844",
              "stop_name": "246",
              "stop_num": "60-145-b12-1.329.O"
            },
            {
              "stop_lat": "53.2332284616912",
              "stop_lon": "-6.12356259217894",
              "stop_name": "247",
              "stop_num": "60-145-b12-1.329.O"
            },
            {
              "stop_lat": "53.2331478569546",
              "stop_lon": "-6.12358109852707",
              "stop_name": "248",
              "stop_num": "60-145-b12-1.329.O"
            },
            {
              "stop_lat": "53.2331055385462",
              "stop_lon": "-6.12374773632853",
              "stop_name": "249",
              "stop_num": "60-145-b12-1.329.O"
            },
            {
              "stop_lat": "53.2323344769808",
              "stop_lon": "-6.12387134108977",
              "stop_name": "250",
              "stop_num": "60-145-b12-1.329.O"
            },
            {
              "stop_lat": "53.2311941989699",
              "stop_lon": "-6.12395116625083",
              "stop_name": "251",
              "stop_num": "60-145-b12-1.329.O"
            },
            {
              "stop_lat": "53.230064316923",
              "stop_lon": "-6.12412040917191",
              "stop_name": "252",
              "stop_num": "60-145-b12-1.329.O"
            },
            {
              "stop_lat": "53.2288257043895",
              "stop_lon": "-6.12423447932048",
              "stop_name": "253",
              "stop_num": "60-145-b12-1.329.O"
            },
            {
              "stop_lat": "53.228770396811",
              "stop_lon": "-6.1241470226595",
              "stop_name": "254",
              "stop_num": "60-145-b12-1.329.O"
            },
            {
              "stop_lat": "53.2287259566854",
              "stop_lon": "-6.12417892375762",
              "stop_name": "255",
              "stop_num": "60-145-b12-1.329.O"
            },
            {
              "stop_lat": "53.2287179169711",
              "stop_lon": "-6.12423919157891",
              "stop_name": "256",
              "stop_num": "60-145-b12-1.329.O"
            },
            {
              "stop_lat": "53.2282607629425",
              "stop_lon": "-6.12431909282602",
              "stop_name": "257",
              "stop_num": "60-145-b12-1.329.O"
            },
            {
              "stop_lat": "53.2278496983059",
              "stop_lon": "-6.12447187144549",
              "stop_name": "258",
              "stop_num": "60-145-b12-1.329.O"
            },
            {
              "stop_lat": "53.227393721976",
              "stop_lon": "-6.12462660998357",
              "stop_name": "259",
              "stop_num": "60-145-b12-1.329.O"
            },
            {
              "stop_lat": "53.2269455498229",
              "stop_lon": "-6.12470611173463",
              "stop_name": "260",
              "stop_num": "60-145-b12-1.329.O"
            },
            {
              "stop_lat": "53.2261061609953",
              "stop_lon": "-6.12505733718827",
              "stop_name": "261",
              "stop_num": "60-145-b12-1.329.O"
            },
            {
              "stop_lat": "53.2257385935308",
              "stop_lon": "-6.1251183318762",
              "stop_name": "262",
              "stop_num": "60-145-b12-1.329.O"
            },
            {
              "stop_lat": "53.2251989493102",
              "stop_lon": "-6.12509697644147",
              "stop_name": "263",
              "stop_num": "60-145-b12-1.329.O"
            },
            {
              "stop_lat": "53.2247465371388",
              "stop_lon": "-6.12490705539588",
              "stop_name": "264",
              "stop_num": "60-145-b12-1.329.O"
            },
            {
              "stop_lat": "53.224166016811",
              "stop_lon": "-6.12457296158345",
              "stop_name": "265",
              "stop_num": "60-145-b12-1.329.O"
            },
            {
              "stop_lat": "53.2240111975056",
              "stop_lon": "-6.12444493065869",
              "stop_name": "266",
              "stop_num": "60-145-b12-1.329.O"
            },
            {
              "stop_lat": "53.2233881481326",
              "stop_lon": "-6.1236933453844",
              "stop_name": "267",
              "stop_num": "60-145-b12-1.329.O"
            },
            {
              "stop_lat": "53.2221399125933",
              "stop_lon": "-6.12205554176598",
              "stop_name": "268",
              "stop_num": "60-145-b12-1.329.O"
            },
            {
              "stop_lat": "53.2217922160823",
              "stop_lon": "-6.12166638614811",
              "stop_name": "269",
              "stop_num": "60-145-b12-1.329.O"
            },
            {
              "stop_lat": "53.2210441058368",
              "stop_lon": "-6.12096528377108",
              "stop_name": "270",
              "stop_num": "60-145-b12-1.329.O"
            },
            {
              "stop_lat": "53.2208169524525",
              "stop_lon": "-6.1208104892892",
              "stop_name": "271",
              "stop_num": "60-145-b12-1.329.O"
            },
            {
              "stop_lat": "53.2205902709977",
              "stop_lon": "-6.1206856282541",
              "stop_name": "272",
              "stop_num": "60-145-b12-1.329.O"
            },
            {
              "stop_lat": "53.2196773949346",
              "stop_lon": "-6.12036617758021",
              "stop_name": "273",
              "stop_num": "60-145-b12-1.329.O"
            },
            {
              "stop_lat": "53.2187619204026",
              "stop_lon": "-6.11988212203148",
              "stop_name": "274",
              "stop_num": "60-145-b12-1.329.O"
            },
            {
              "stop_lat": "53.2184094861124",
              "stop_lon": "-6.11976278032478",
              "stop_name": "275",
              "stop_num": "60-145-b12-1.329.O"
            },
            {
              "stop_lat": "53.2159249449999",
              "stop_lon": "-6.11952719324942",
              "stop_name": "276",
              "stop_num": "60-145-b12-1.329.O"
            },
            {
              "stop_lat": "53.2145757133062",
              "stop_lon": "-6.11946650390217",
              "stop_name": "277",
              "stop_num": "60-145-b12-1.329.O"
            },
            {
              "stop_lat": "53.21418711316",
              "stop_lon": "-6.11933378675202",
              "stop_name": "278",
              "stop_num": "60-145-b12-1.329.O"
            },
            {
              "stop_lat": "53.2139963592826",
              "stop_lon": "-6.11920737786356",
              "stop_name": "279",
              "stop_num": "60-145-b12-1.329.O"
            },
            {
              "stop_lat": "53.213722874761",
              "stop_lon": "-6.11896480397586",
              "stop_name": "280",
              "stop_num": "60-145-b12-1.329.O"
            },
            {
              "stop_lat": "53.2137034926337",
              "stop_lon": "-6.11887581011837",
              "stop_name": "281",
              "stop_num": "60-145-b12-1.329.O"
            },
            {
              "stop_lat": "53.2136205256421",
              "stop_lon": "-6.11874468121399",
              "stop_name": "282",
              "stop_num": "60-145-b12-1.329.O"
            },
            {
              "stop_lat": "53.2135302302776",
              "stop_lon": "-6.11871869053243",
              "stop_name": "283",
              "stop_num": "60-145-b12-1.329.O"
            },
            {
              "stop_lat": "53.213432134048",
              "stop_lon": "-6.11876791060939",
              "stop_name": "284",
              "stop_num": "60-145-b12-1.329.O"
            },
            {
              "stop_lat": "53.2133416024031",
              "stop_lon": "-6.11872695660951",
              "stop_name": "285",
              "stop_num": "60-145-b12-1.329.O"
            },
            {
              "stop_lat": "53.2130359685948",
              "stop_lon": "-6.11872537631764",
              "stop_name": "286",
              "stop_num": "60-145-b12-1.329.O"
            },
            {
              "stop_lat": "53.2128459229786",
              "stop_lon": "-6.11864386301216",
              "stop_name": "287",
              "stop_num": "60-145-b12-1.329.O"
            },
            {
              "stop_lat": "53.2112588979499",
              "stop_lon": "-6.11775513580698",
              "stop_name": "288",
              "stop_num": "60-145-b12-1.329.O"
            },
            {
              "stop_lat": "53.21104048636",
              "stop_lon": "-6.11758503604159",
              "stop_name": "289",
              "stop_num": "60-145-b12-1.329.O"
            },
            {
              "stop_lat": "53.2108208923049",
              "stop_lon": "-6.11734012556573",
              "stop_name": "290",
              "stop_num": "60-145-b12-1.329.O"
            },
            {
              "stop_lat": "53.2106287175459",
              "stop_lon": "-6.11712396064021",
              "stop_name": "291",
              "stop_num": "60-145-b12-1.329.O"
            },
            {
              "stop_lat": "53.2101327948832",
              "stop_lon": "-6.11645696876196",
              "stop_name": "292",
              "stop_num": "60-145-b12-1.329.O"
            },
            {
              "stop_lat": "53.2095427860378",
              "stop_lon": "-6.11552461760902",
              "stop_name": "293",
              "stop_num": "60-145-b12-1.329.O"
            },
            {
              "stop_lat": "53.2093595903426",
              "stop_lon": "-6.11530807290668",
              "stop_name": "294",
              "stop_num": "60-145-b12-1.329.O"
            },
            {
              "stop_lat": "53.2081419982089",
              "stop_lon": "-6.11447817395338",
              "stop_name": "295",
              "stop_num": "60-145-b12-1.329.O"
            },
            {
              "stop_lat": "53.2077311651386",
              "stop_lon": "-6.11407700460041",
              "stop_name": "296",
              "stop_num": "60-145-b12-1.329.O"
            },
            {
              "stop_lat": "53.2072645419235",
              "stop_lon": "-6.11355852069716",
              "stop_name": "297",
              "stop_num": "60-145-b12-1.329.O"
            },
            {
              "stop_lat": "53.2071179826267",
              "stop_lon": "-6.11338530056987",
              "stop_name": "298",
              "stop_num": "60-145-b12-1.329.O"
            },
            {
              "stop_lat": "53.206877334953",
              "stop_lon": "-6.11294672910452",
              "stop_name": "299",
              "stop_num": "60-145-b12-1.329.O"
            },
            {
              "stop_lat": "53.2066368960203",
              "stop_lon": "-6.11195421134308",
              "stop_name": "300",
              "stop_num": "60-145-b12-1.329.O"
            },
            {
              "stop_lat": "53.2065144354474",
              "stop_lon": "-6.11160028307936",
              "stop_name": "301",
              "stop_num": "60-145-b12-1.329.O"
            },
            {
              "stop_lat": "53.2061127795027",
              "stop_lon": "-6.11064481691815",
              "stop_name": "302",
              "stop_num": "60-145-b12-1.329.O"
            },
            {
              "stop_lat": "53.2057236589964",
              "stop_lon": "-6.10991338296348",
              "stop_name": "303",
              "stop_num": "60-145-b12-1.329.O"
            },
            {
              "stop_lat": "53.2054957795411",
              "stop_lon": "-6.10971381885677",
              "stop_name": "304",
              "stop_num": "60-145-b12-1.329.O"
            },
            {
              "stop_lat": "53.2051601128263",
              "stop_lon": "-6.10951900200781",
              "stop_name": "305",
              "stop_num": "60-145-b12-1.329.O"
            },
            {
              "stop_lat": "53.2047171337419",
              "stop_lon": "-6.1093588542864",
              "stop_name": "306",
              "stop_num": "60-145-b12-1.329.O"
            },
            {
              "stop_lat": "53.2042311427772",
              "stop_lon": "-6.10932036812083",
              "stop_name": "307",
              "stop_num": "60-145-b12-1.329.O"
            },
            {
              "stop_lat": "53.2040065866445",
              "stop_lon": "-6.1093302544801",
              "stop_name": "308",
              "stop_num": "60-145-b12-1.329.O"
            },
            {
              "stop_lat": "53.2037111222509",
              "stop_lon": "-6.10940314402513",
              "stop_name": "309",
              "stop_num": "60-145-b12-1.329.O"
            },
            {
              "stop_lat": "53.2031038905556",
              "stop_lon": "-6.10965442884657",
              "stop_name": "310",
              "stop_num": "60-145-b12-1.329.O"
            },
            {
              "stop_lat": "53.2026401368577",
              "stop_lon": "-6.10988442181045",
              "stop_name": "311",
              "stop_num": "60-145-b12-1.329.O"
            },
            {
              "stop_lat": "53.2023198613391",
              "stop_lon": "-6.11009312602334",
              "stop_name": "312",
              "stop_num": "60-145-b12-1.329.O"
            },
            {
              "stop_lat": "53.2015554556722",
              "stop_lon": "-6.11063573092536",
              "stop_name": "313",
              "stop_num": "60-145-b12-1.329.O"
            },
            {
              "stop_lat": "53.2005272715146",
              "stop_lon": "-6.11154917902549",
              "stop_name": "314",
              "stop_num": "60-145-b12-1.329.O"
            },
            {
              "stop_lat": "53.1995527363763",
              "stop_lon": "-6.11244525604307",
              "stop_name": "315",
              "stop_num": "60-145-b12-1.329.O"
            },
            {
              "stop_lat": "53.1990677172468",
              "stop_lon": "-6.11303538350841",
              "stop_name": "316",
              "stop_num": "60-145-b12-1.329.O"
            },
            {
              "stop_lat": "53.1987169554099",
              "stop_lon": "-6.11358966394816",
              "stop_name": "317",
              "stop_num": "60-145-b12-1.329.O"
            },
            {
              "stop_lat": "53.1985621432715",
              "stop_lon": "-6.11403055195263",
              "stop_name": "318",
              "stop_num": "60-145-b12-1.329.O"
            },
            {
              "stop_lat": "53.1982901001117",
              "stop_lon": "-6.11501544838841",
              "stop_name": "319",
              "stop_num": "60-145-b12-1.329.O"
            },
            {
              "stop_lat": "53.1981518272474",
              "stop_lon": "-6.11536579045915",
              "stop_name": "320",
              "stop_num": "60-145-b12-1.329.O"
            },
            {
              "stop_lat": "53.1979426414728",
              "stop_lon": "-6.11577911446727",
              "stop_name": "321",
              "stop_num": "60-145-b12-1.329.O"
            },
            {
              "stop_lat": "53.197696815387",
              "stop_lon": "-6.11614913645702",
              "stop_name": "322",
              "stop_num": "60-145-b12-1.329.O"
            },
            {
              "stop_lat": "53.1975112623899",
              "stop_lon": "-6.11635186096282",
              "stop_name": "323",
              "stop_num": "60-145-b12-1.329.O"
            },
            {
              "stop_lat": "53.1971737195559",
              "stop_lon": "-6.11660615222433",
              "stop_name": "324",
              "stop_num": "60-145-b12-1.329.O"
            },
            {
              "stop_lat": "53.196317567516",
              "stop_lon": "-6.11703285230809",
              "stop_name": "325",
              "stop_num": "60-145-b12-1.329.O"
            },
            {
              "stop_lat": "53.195890200065",
              "stop_lon": "-6.11729106767902",
              "stop_name": "326",
              "stop_num": "60-145-b12-1.329.O"
            },
            {
              "stop_lat": "53.1957575931948",
              "stop_lon": "-6.11743158786412",
              "stop_name": "327",
              "stop_num": "60-145-b12-1.329.O"
            },
            {
              "stop_lat": "53.1953616621798",
              "stop_lon": "-6.11797280001739",
              "stop_name": "328",
              "stop_num": "60-145-b12-1.329.O"
            },
            {
              "stop_lat": "53.1951070828406",
              "stop_lon": "-6.1183581374859",
              "stop_name": "329",
              "stop_num": "60-145-b12-1.329.O"
            },
            {
              "stop_lat": "53.1947156349997",
              "stop_lon": "-6.11918351375646",
              "stop_name": "330",
              "stop_num": "60-145-b12-1.329.O"
            },
            {
              "stop_lat": "53.1955623118065",
              "stop_lon": "-6.12043365119465",
              "stop_name": "331",
              "stop_num": "60-145-b12-1.329.O"
            },
            {
              "stop_lat": "53.196245407095",
              "stop_lon": "-6.1215712479183",
              "stop_name": "332",
              "stop_num": "60-145-b12-1.329.O"
            },
            {
              "stop_lat": "53.1967994387568",
              "stop_lon": "-6.12250496950017",
              "stop_name": "333",
              "stop_num": "60-145-b12-1.329.O"
            },
            {
              "stop_lat": "53.1968476508354",
              "stop_lon": "-6.12271241379624",
              "stop_name": "334",
              "stop_num": "60-145-b12-1.329.O"
            },
            {
              "stop_lat": "53.1968599332506",
              "stop_lon": "-6.12292142859955",
              "stop_name": "335",
              "stop_num": "60-145-b12-1.329.O"
            },
            {
              "stop_lat": "53.1968384070432",
              "stop_lon": "-6.12326663236576",
              "stop_name": "336",
              "stop_num": "60-145-b12-1.329.O"
            },
            {
              "stop_lat": "53.1968511597591",
              "stop_lon": "-6.12350556264928",
              "stop_name": "337",
              "stop_num": "60-145-b12-1.329.O"
            },
            {
              "stop_lat": "53.1969170991583",
              "stop_lon": "-6.1236972659763",
              "stop_name": "338",
              "stop_num": "60-145-b12-1.329.O"
            },
            {
              "stop_lat": "53.1967762090444",
              "stop_lon": "-6.12388303526732",
              "stop_name": "339",
              "stop_num": "60-145-b12-1.329.O"
            },
            {
              "stop_lat": "53.196033905413",
              "stop_lon": "-6.12526254585737",
              "stop_name": "340",
              "stop_num": "60-145-b12-1.329.O"
            },
            {
              "stop_lat": "53.1955499974668",
              "stop_lon": "-6.12592726702533",
              "stop_name": "341",
              "stop_num": "60-145-b12-1.329.O"
            },
            {
              "stop_lat": "53.1945540470764",
              "stop_lon": "-6.12718305449292",
              "stop_name": "342",
              "stop_num": "60-145-b12-1.329.O"
            },
            {
              "stop_lat": "53.1940157636052",
              "stop_lon": "-6.12782016616717",
              "stop_name": "343",
              "stop_num": "60-145-b12-1.329.O"
            },
            {
              "stop_lat": "53.1935732272978",
              "stop_lon": "-6.12825852200434",
              "stop_name": "344",
              "stop_num": "60-145-b12-1.329.O"
            },
            {
              "stop_lat": "53.1934134249857",
              "stop_lon": "-6.12838521832179",
              "stop_name": "345",
              "stop_num": "60-145-b12-1.329.O"
            },
            {
              "stop_lat": "53.1922205966988",
              "stop_lon": "-6.1291256336667",
              "stop_name": "346",
              "stop_num": "60-145-b12-1.329.O"
            },
            {
              "stop_lat": "53.1917775854598",
              "stop_lon": "-6.1295340454905",
              "stop_name": "347",
              "stop_num": "60-145-b12-1.329.O"
            },
            {
              "stop_lat": "53.191545274843",
              "stop_lon": "-6.12905027786236",
              "stop_name": "348",
              "stop_num": "60-145-b12-1.329.O"
            },
            {
              "stop_lat": "53.1900402883061",
              "stop_lon": "-6.12594310863198",
              "stop_name": "349",
              "stop_num": "60-145-b12-1.329.O"
            },
            {
              "stop_lat": "53.1898441281515",
              "stop_lon": "-6.12547276784795",
              "stop_name": "350",
              "stop_num": "60-145-b12-1.329.O"
            },
            {
              "stop_lat": "53.1890737234394",
              "stop_lon": "-6.1262097443824",
              "stop_name": "351",
              "stop_num": "60-145-b12-1.329.O"
            },
            {
              "stop_lat": "53.1885082618256",
              "stop_lon": "-6.12683300509071",
              "stop_name": "352",
              "stop_num": "60-145-b12-1.329.O"
            },
            {
              "stop_lat": "53.1882791887369",
              "stop_lon": "-6.12712732551652",
              "stop_name": "353",
              "stop_num": "60-145-b12-1.329.O"
            },
            {
              "stop_lat": "53.1879607614811",
              "stop_lon": "-6.12745546642548",
              "stop_name": "354",
              "stop_num": "60-145-b12-1.329.O"
            },
            {
              "stop_lat": "53.1876418631198",
              "stop_lon": "-6.12775369342855",
              "stop_name": "355",
              "stop_num": "60-145-b12-1.329.O"
            },
            {
              "stop_lat": "53.1863814072309",
              "stop_lon": "-6.12876632568521",
              "stop_name": "356",
              "stop_num": "60-145-b12-1.329.O"
            },
            {
              "stop_lat": "53.1858570851956",
              "stop_lon": "-6.12914829582901",
              "stop_name": "357",
              "stop_num": "60-145-b12-1.329.O"
            },
            {
              "stop_lat": "53.1851566366605",
              "stop_lon": "-6.12976238055501",
              "stop_name": "358",
              "stop_num": "60-145-b12-1.329.O"
            },
            {
              "stop_lat": "53.1846758144162",
              "stop_lon": "-6.13005265229668",
              "stop_name": "359",
              "stop_num": "60-145-b12-1.329.O"
            },
            {
              "stop_lat": "53.1840333084596",
              "stop_lon": "-6.13034995137977",
              "stop_name": "360",
              "stop_num": "60-145-b12-1.329.O"
            },
            {
              "stop_lat": "53.1833399581936",
              "stop_lon": "-6.13084397497817",
              "stop_name": "361",
              "stop_num": "60-145-b12-1.329.O"
            },
            {
              "stop_lat": "53.1830837575578",
              "stop_lon": "-6.13055585450572",
              "stop_name": "362",
              "stop_num": "60-145-b12-1.329.O"
            },
            {
              "stop_lat": "53.1828289646685",
              "stop_lon": "-6.13035745455215",
              "stop_name": "363",
              "stop_num": "60-145-b12-1.329.O"
            },
            {
              "stop_lat": "53.1826658733038",
              "stop_lon": "-6.13027477133252",
              "stop_name": "364",
              "stop_num": "60-145-b12-1.329.O"
            },
            {
              "stop_lat": "53.182340864189",
              "stop_lon": "-6.13018417013237",
              "stop_name": "365",
              "stop_num": "60-145-b12-1.329.O"
            }
          ],
          "shapes": [
          ]
        }
      ]
    },
    "id": "43103d87-f92e-4a6c-85c7-99e71057423d",
    "priority": 0,
    "timeToLive": {
      "unlimited": true
    },
    "times": {
      "unlimited": true
    }
  }
]